MotionPlanningEnv/collisionObstacle.py
MotionPlanningEnv/dynamicSphereObstacle.py
MotionPlanningEnv/obstacleCreator.py
MotionPlanningEnv/sphereObstacle.py
MotionPlanningEnv/sphere_smooth.mtl
MotionPlanningEnv/sphere_smooth.obj
MotionPlanningEnv/urdfObstacle.py
MotionPlanningGoal/dynamicSubGoal.py
MotionPlanningGoal/goalComposition.py
MotionPlanningGoal/staticJointSpaceSubGoal.py
MotionPlanningGoal/staticSubGoal.py
MotionPlanningGoal/subGoal.py
MotionPlanningGoal/subGoalCreator.py
MotionPlanningSceneHelpers/analyticTrajectory.py
MotionPlanningSceneHelpers/motionPlanningComponent.py
MotionPlanningSceneHelpers/referenceTrajectory.py
MotionPlanningSceneHelpers/splineTrajectory.py
motion_planning_scenes-0.4.0.dist-info/WHEEL
motion_planning_scenes-0.4.0.dist-info/METADATA
motion_planning_scenes-0.4.0.dist-info/RECORD
